{
"type": "FeatureCollection",
"name": "zoo_enceph_humans",
"crs": { "type": "name", "properties": { "name": "urn:ogc:def:crs:OGC:1.3:CRS84" } },
"features": [
{ "type": "Feature", "properties": { "Municipal_": "თეთრიწყაროს მუნიც", "Region_Geo": "ქვემო ქართლი", "Encepaliti": 1.0, "disease_geo": "ენცეფალიტი (ადამიანები)" }, "geometry": { "type": "Point", "coordinates": [ 44.667068000568889, 41.594584000134901 ] } },
{ "type": "Feature", "properties": { "Municipal_": "ქალაქ რუსთავის მუნ", "Region_Geo": "ქვემო ქართლი", "Encepaliti": 1.0, "disease_geo": "ენცეფალიტი (ადამიანები)" }, "geometry": { "type": "Point", "coordinates": [ 45.043037000417726, 41.522561000210835 ] } },
{ "type": "Feature", "properties": { "Municipal_": "ქალაქ რუსთავის მუნ", "Region_Geo": "ქვემო ქართლი", "Encepaliti": 1.0, "disease_geo": "ენცეფალიტი (ადამიანები)" }, "geometry": { "type": "Point", "coordinates": [ 45.043037000417726, 41.522561000210835 ] } },
{ "type": "Feature", "properties": { "Municipal_": "თეთრიწყაროს მუნიც", "Region_Geo": "ქვემო ქართლი", "Encepaliti": 1.0, "disease_geo": "ენცეფალიტი (ადამიანები)" }, "geometry": { "type": "Point", "coordinates": [ 44.411491999415908, 41.506527999766782 ] } },
{ "type": "Feature", "properties": { "Municipal_": "თეთრიწყაროს მუნიც", "Region_Geo": "ქვემო ქართლი", "Encepaliti": 1.0, "disease_geo": "ენცეფალიტი (ადამიანები)" }, "geometry": { "type": "Point", "coordinates": [ 44.411491999415908, 41.506527999766782 ] } },
{ "type": "Feature", "properties": { "Municipal_": "დმანისის მუნიციპა", "Region_Geo": "ქვემო ქართლი", "Encepaliti": 1.0, "disease_geo": "ენცეფალიტი (ადამიანები)" }, "geometry": { "type": "Point", "coordinates": [ 44.364180999559842, 41.351511000071582 ] } },
{ "type": "Feature", "properties": { "Municipal_": "დმანისის მუნიციპა", "Region_Geo": "ქვემო ქართლი", "Encepaliti": 1.0, "disease_geo": "ენცეფალიტი (ადამიანები)" }, "geometry": { "type": "Point", "coordinates": [ 44.364180999559842, 41.351511000071582 ] } },
{ "type": "Feature", "properties": { "Municipal_": "თეთრიწყაროს მუნიც", "Region_Geo": "ქვემო ქართლი", "Encepaliti": 1.0, "disease_geo": "ენცეფალიტი (ადამიანები)" }, "geometry": { "type": "Point", "coordinates": [ 44.669218999694763, 41.594138999566169 ] } },
{ "type": "Feature", "properties": { "Municipal_": "თეთრიწყაროს მუნიც", "Region_Geo": "ქვემო ქართლი", "Encepaliti": 1.0, "disease_geo": "ენცეფალიტი (ადამიანები)" }, "geometry": { "type": "Point", "coordinates": [ 44.669218999694763, 41.594138999566169 ] } },
{ "type": "Feature", "properties": { "Municipal_": "ბოლნისის მუნიციპა", "Region_Geo": "ქვემო ქართლი", "Encepaliti": 1.0, "disease_geo": "ენცეფალიტი (ადამიანები)" }, "geometry": { "type": "Point", "coordinates": [ 44.67788000006373, 41.446036999855998 ] } },
{ "type": "Feature", "properties": { "Municipal_": "ბოლნისის მუნიციპა", "Region_Geo": "ქვემო ქართლი", "Encepaliti": 1.0, "disease_geo": "ენცეფალიტი (ადამიანები)" }, "geometry": { "type": "Point", "coordinates": [ 44.67788000006373, 41.446036999855998 ] } },
{ "type": "Feature", "properties": { "Municipal_": "ბოლნისის მუნიციპა", "Region_Geo": "ქვემო ქართლი", "Encepaliti": 1.0, "disease_geo": "ენცეფალიტი (ადამიანები)" }, "geometry": { "type": "Point", "coordinates": [ 44.67788000006373, 41.446036999855998 ] } }
]
}
